CowtransferAPI/__init__.py
CowtransferAPI/__main__.py
CowtransferAPI/__version__.py
CowtransferAPI/cli.py
CowtransferAPI/upload.py
CowtransferAPI-0.0.1.dist-info/LICENSE
CowtransferAPI-0.0.1.dist-info/METADATA
CowtransferAPI-0.0.1.dist-info/WHEEL
CowtransferAPI-0.0.1.dist-info/top_level.txt
CowtransferAPI-0.0.1.dist-info/RECORD
