Metadata-Version: 2.1
Name: CowtransferAPI
Version: 0.0.1
Summary: CowTransfer API for Python 3.6+ 适用于 Python 3.6+ 奶牛快传第三方API
Home-page: https://github.com/kitUIN/CowtransferAPI
Author: kitUIN
Author-email: kulujun@gmail.com
License: MIT License
Platform: UNKNOWN
Classifier: Programming Language :: Python :: 3
Classifier: License :: OSI Approved :: MIT License
Classifier: Operating System :: OS Independent
Requires-Python: >=3.6
Requires-Dist: typer (~=0.3.2)
Requires-Dist: rich (~=9.10.0)
Requires-Dist: colorama
Requires-Dist: shellingham
Requires-Dist: python-magic (~=0.4.18)
Requires-Dist: python-magic-bin
Requires-Dist: requests (~=2.25.1)
Requires-Dist: requests-toolbelt
Requires-Dist: urllib3 (~=1.26.3)
